[
 {
  "class_name": "7",
  "docstatus": 0,
  "doctype": "Class",
  "modified": "2024-07-21 01:11:01.145936",
  "name": "7"
 },
 {
  "class_name": "9",
  "docstatus": 0,
  "doctype": "Class",
  "modified": "2024-07-21 01:11:10.479292",
  "name": "9"
 },
 {
  "class_name": "10",
  "docstatus": 0,
  "doctype": "Class",
  "modified": "2024-07-21 01:11:15.492134",
  "name": "10"
 },
 {
  "class_name": "6",
  "docstatus": 0,
  "doctype": "Class",
  "modified": "2024-07-21 01:10:56.106107",
  "name": "6"
 },
 {
  "class_name": "8",
  "docstatus": 0,
  "doctype": "Class",
  "modified": "2024-07-21 01:11:05.939618",
  "name": "8"
 }
]